odoo/addons/l10n_be_cooperator_national_number/README.rst
odoo/addons/l10n_be_cooperator_national_number/__init__.py
odoo/addons/l10n_be_cooperator_national_number/__manifest__.py
odoo/addons/l10n_be_cooperator_national_number/i18n/it.po
odoo/addons/l10n_be_cooperator_national_number/i18n/l10n_be_cooperator_national_number.pot
odoo/addons/l10n_be_cooperator_national_number/migrations/14.0.1.1.0/post-migration.py
odoo/addons/l10n_be_cooperator_national_number/models/__init__.py
odoo/addons/l10n_be_cooperator_national_number/models/company.py
odoo/addons/l10n_be_cooperator_national_number/models/res_partner.py
odoo/addons/l10n_be_cooperator_national_number/models/subscription_request.py
odoo/addons/l10n_be_cooperator_national_number/readme/CONTRIBUTORS.rst
odoo/addons/l10n_be_cooperator_national_number/readme/DESCRIPTION.rst
odoo/addons/l10n_be_cooperator_national_number/readme/USAGE.rst
odoo/addons/l10n_be_cooperator_national_number/static/description/icon.png
odoo/addons/l10n_be_cooperator_national_number/static/description/index.html
odoo/addons/l10n_be_cooperator_national_number/tests/__init__.py
odoo/addons/l10n_be_cooperator_national_number/tests/test_cooperator_national_number.py
odoo/addons/l10n_be_cooperator_national_number/views/res_company_view.xml
odoo/addons/l10n_be_cooperator_national_number/views/subscription_request_view.xml
odoo14_addon_l10n_be_cooperator_national_number-14.0.1.1.1.dev10.dist-info/METADATA
odoo14_addon_l10n_be_cooperator_national_number-14.0.1.1.1.dev10.dist-info/WHEEL
odoo14_addon_l10n_be_cooperator_national_number-14.0.1.1.1.dev10.dist-info/top_level.txt
odoo14_addon_l10n_be_cooperator_national_number-14.0.1.1.1.dev10.dist-info/RECORD
