Metadata-Version: 2.1
Name: odoo14-addon-l10n_be_cooperator_national_number
Version: 14.0.1.1.1.dev10
Summary: Ask for Belgian National Number in Cooperative Subscription Request.
Home-page: https://github.com/OCA/cooperative
Author: Coop IT Easy SC, Odoo Community Association (OCA)
Author-email: support@odoo-community.org
License: AGPL-3
Classifier: Programming Language :: Python
Classifier: Framework :: Odoo
Classifier: Framework :: Odoo :: 14.0
Classifier: License :: OSI Approved :: GNU Affero General Public License v3
Requires-Python: >=3.6
Requires-Dist: odoo14-addon-cooperator
Requires-Dist: odoo14-addon-l10n-be-national-number
Requires-Dist: odoo<14.1dev,>=14.0a
